{
    "Ar36": {
        "error": 0.0017419716421028337,
        "error_type": "SEM",
        "filter_outliers_dict": {
            "filter_outliers": true,
            "iterations": 1,
            "std_devs": 3,
            "use_iqr_filtering": false,
            "use_standard_deviation_filtering": false
        },
        "fit": "linear",
        "fn": 339,
        "include_baseline_error": true,
        "n": 340,
        "outlier_excluded": [
            267
        ],
        "reviewed": true,
        "user_excluded": [],
        "value": 1.3488956088271093
    },
    "Ar37": {
        "error": 0.017288889297264798,
        "error_type": "SEM",
        "filter_outliers_dict": {
            "filter_outliers": true,
            "iterations": 1,
            "std_devs": 3,
            "use_iqr_filtering": false,
            "use_standard_deviation_filtering": false
        },
        "fit": "linear",
        "fn": 340,
        "include_baseline_error": true,
        "n": 340,
        "outlier_excluded": [],
        "reviewed": true,
        "user_excluded": [],
        "value": 0.471213989706407
    },
    "Ar38": {
        "error": 0.006154796891621464,
        "error_type": "SEM",
        "filter_outliers_dict": {
            "filter_outliers": true,
            "iterations": 1,
            "std_devs": 3,
            "use_iqr_filtering": false,
            "use_standard_deviation_filtering": false
        },
        "fit": "linear",
        "fn": 339,
        "include_baseline_error": true,
        "n": 340,
        "outlier_excluded": [
            71
        ],
        "reviewed": true,
        "user_excluded": [],
        "value": 0.84614965807848
    },
    "Ar39": {
        "error": 0.00882220132362527,
        "error_type": "SEM",
        "filter_outliers_dict": {
            "filter_outliers": true,
            "iterations": 1,
            "std_devs": 3,
            "use_iqr_filtering": false,
            "use_standard_deviation_filtering": false
        },
        "fit": "linear",
        "fn": 339,
        "include_baseline_error": true,
        "n": 340,
        "outlier_excluded": [
            222
        ],
        "reviewed": true,
        "user_excluded": [],
        "value": 40.21464479909869
    },
    "Ar40": {
        "error": 0.0644940282139076,
        "error_type": "SEM",
        "filter_outliers_dict": {
            "filter_outliers": true,
            "iterations": 1,
            "std_devs": 3,
            "use_iqr_filtering": false,
            "use_standard_deviation_filtering": false
        },
        "fit": "parabolic",
        "fn": 339,
        "include_baseline_error": true,
        "n": 340,
        "outlier_excluded": [
            19
        ],
        "reviewed": true,
        "user_excluded": [],
        "value": 622.4647316646181
    }
}